monerosub/__init__.py
monerosub/monerosub.py
monerosub-1.0.0.dist-info/METADATA
monerosub-1.0.0.dist-info/WHEEL
monerosub-1.0.0.dist-info/top_level.txt
monerosub-1.0.0.dist-info/RECORD
